_judy.cpython-310-aarch64-linux-gnu.so
judy-1.0.20.dist-info/top_level.txt
judy-1.0.20.dist-info/RECORD
judy-1.0.20.dist-info/LICENSE
judy-1.0.20.dist-info/METADATA
judy-1.0.20.dist-info/WHEEL
judy/__init__.py
judy/__init__.pyi
judy/py.typed
