Metadata-Version: 2.1
Name: judy
Version: 1.0.20
Summary: A Python wrapper for Judy arrays, which provide fast and space-efficient integer mappings and integer sets, along with ranged ordered iterations
Home-page: https://github.com/arnimarj/py-judy/
Maintainer: Arni Mar Jonsson
Maintainer-email: arnimarj@gmail.com
Classifier: Development Status :: 5 - Production/Stable
Classifier: Environment :: Other Environment
Classifier: Intended Audience :: Developers
Classifier: License :: OSI Approved :: GNU Library or Lesser General Public License (LGPL)
Classifier: Operating System :: POSIX
Classifier: Programming Language :: C
Classifier: Programming Language :: Python
Classifier: Programming Language :: Python :: 3
Classifier: Programming Language :: Python :: 3.8
Classifier: Programming Language :: Python :: 3.9
Classifier: Programming Language :: Python :: 3.10
Classifier: Programming Language :: Python :: 3.11
Classifier: Programming Language :: Python :: 3.12
Classifier: Programming Language :: Python :: 3.13
Classifier: Topic :: Database
Classifier: Topic :: Software Development :: Libraries
License-File: LICENSE
